{"49101241": {"ad_url": "https://www.webmotors.com.br/comprar/fiat/500/14-cult-8v-flex-2p-manual/2-portas/2011-2012/49101241", "car": {"UniqueId": 49101241, "PhotoPath": "2023\\202311\\20231105\\fiat-500-1.4-cult-8v-flex-2p-manual-WMIMAGEM20195774138.jpg", "Specification": {"Title": "FIAT 500 1.4 CULT 8V FLEX 2P MANUAL", "Make": {"id": 4, "Value": "FIAT"}, "Model": {"id": 2978, "Value": "500"}, "Version": {"id": 343961, "Value": "1.4 CULT 8V FLEX 2P MANUAL"}, "YearFabrication": "2011", "YearModel": 2012.0, "Odometer": 85000.0, "Transmission": "Manual", "NumberPorts": "2", "BodyType": "Hatchback", "VehicleAttributes": [{"Name": "IPVA pago"}, {"Name": "Licenciado"}], "Armored": "N", "Color": {"IdPrimary": "30409", "Primary": "Prata"}}, "Seller": {"Id": 13939463, "SellerType": "PF", "City": "Osasco", "State": "S\u00e3o Paulo (SP)", "AdType": {"id": 4, "Value": "Pessoa F\u00edsica"}, "BudgetInvestimento": 0, "DealerScore": 0, "CarDelivery": false, "TrocaComTroco": false, "ExceededPlan": false, "Localization": [{"State": "S\u00e3o Paulo (SP)", "City": "Osasco", "Country": "Brasil", "Neighborhood": "", "ZipCode": "06286010", "AbbrState": "SP"}]}, "Prices": {"Price": 39500.0, "SearchPrice": 39500.0}, "ListingType": "U", "ProductCode": "1245", "Channels": [{"id": 48, "Value": "Webmotors"}], "FipePercent": 98, "GoodDeal": true, "IsElegibleVehicleInspection": false, "IsElegible360View": false}}, "52457664": {"ad_url": "https://www.webmotors.com.br/comprar/fiat/500/14-cult-8v-flex-2p-manual/2-portas/2011-2012/52457664", "car": {"UniqueId": 52457664, "PhotoPath": "2024\\202405\\20240529\\fiat-500-1.4-cult-8v-flex-2p-manual-WMIMAGEM14093895254.jpg", "Specification": {"Title": "FIAT 500 1.4 CULT 8V FLEX 2P MANUAL", "Make": {"id": 4, "Value": "FIAT"}, "Model": {"id": 2978, "Value": "500"}, "Version": {"id": 343961, "Value": "1.4 CULT 8V FLEX 2P MANUAL"}, "YearFabrication": "2011", "YearModel": 2012.0, "Odometer": 65000.0, "Transmission": "Manual", "NumberPorts": "2", "BodyType": "Hatchback", "VehicleAttributes": [{"Name": "Aceita troca"}, {"Name": "IPVA pago"}, {"Name": "Licenciado"}], "Armored": "N", "Color": {"IdPrimary": "30413", "Primary": "Vermelho"}}, "Seller": {"Id": 7771010, "SellerType": "PF", "City": "Bauru", "State": "S\u00e3o Paulo (SP)", "AdType": {"id": 4, "Value": "Pessoa F\u00edsica"}, "BudgetInvestimento": 0, "DealerScore": 0, "CarDelivery": false, "TrocaComTroco": false, "ExceededPlan": false, "Localization": [{"State": "S\u00e3o Paulo (SP)", "City": "Bauru", "Country": "Brasil", "Neighborhood": "", "ZipCode": "17014440", "AbbrState": "SP"}]}, "Prices": {"Price": 41000.0, "SearchPrice": 41000.0}, "ListingType": "U", "ProductCode": "3098", "Channels": [{"id": 49, "Value": "CompreAuto"}, {"id": 48, "Value": "Webmotors"}], "LongComment": "Excelente qualidade.  Segunda dona.  Baixa quilometragem.  Flex \u00e9 muito econ\u00f4mico.  ", "FipePercent": 102, "IsElegibleVehicleInspection": false, "IsElegible360View": false}}, "49880208": {"ad_url": "https://www.webmotors.com.br/comprar/fiat/500/14-cult-8v-flex-2p-manual/2-portas/2012-2012/49880208", "car": {"UniqueId": 49880208, "PhotoPath": "2024\\202401\\20240102\\fiat-500-1.4-cult-8v-flex-2p-manual-WMIMAGEM19543300769.jpg", "Specification": {"Title": "FIAT 500 1.4 CULT 8V FLEX 2P MANUAL", "Make": {"id": 4, "Value": "FIAT"}, "Model": {"id": 2978, "Value": "500"}, "Version": {"id": 343961, "Value": "1.4 CULT 8V FLEX 2P MANUAL"}, "YearFabrication": "2012", "YearModel": 2012.0, "Odometer": 85100.0, "Transmission": "Manual", "NumberPorts": "2", "BodyType": "Hatchback", "Armored": "N", "Color": {"IdPrimary": "30410", "Primary": "Preto"}}, "Seller": {"Id": 13297195, "SellerType": "PF", "City": "Santos", "State": "S\u00e3o Paulo (SP)", "AdType": {"id": 4, "Value": "Pessoa F\u00edsica"}, "BudgetInvestimento": 0, "DealerScore": 0, "CarDelivery": false, "TrocaComTroco": false, "ExceededPlan": false, "Localization": [{"State": "S\u00e3o Paulo (SP)", "City": "Santos", "Country": "Brasil", "Neighborhood": "", "ZipCode": "11060303", "AbbrState": "SP"}]}, "Prices": {"Price": 40900.0, "SearchPrice": 40900.0}, "ListingType": "U", "ProductCode": "1245", "Channels": [{"id": 48, "Value": "Webmotors"}], "LongComment": "N\u00c3O FA\u00c7O CONSIGNA\u00c7\u00c3O! Ve\u00edculo conservado, rodas impec\u00e1veis, possui c\u00e2mera de r\u00e9 e frontal, vidros e travas el\u00e9tricas, alarme, chave reserva, banco com regulagem de altura, r\u00e1dio, bateria nova, troca de \u00f3leo e revis\u00e3o completa.  ", "FipePercent": 102, "IsElegibleVehicleInspection": false, "IsElegible360View": false}}, "52461247": {"ad_url": "https://www.webmotors.com.br/comprar/fiat/500/14-cult-8v-flex-2p-manual/2-portas/2011-2012/52461247", "car": {"UniqueId": 52461247, "PhotoPath": "2024\\202405\\20240531\\fiat-500-1.4-cult-8v-flex-2p-manual-wmimagem18271530290.jpg", "Specification": {"Title": "FIAT 500 1.4 CULT 8V FLEX 2P MANUAL", "Make": {"id": 4, "Value": "FIAT"}, "Model": {"id": 2978, "Value": "500"}, "Version": {"id": 343961, "Value": "1.4 CULT 8V FLEX 2P MANUAL"}, "YearFabrication": "2011", "YearModel": 2012.0, "Odometer": 99000.0, "Transmission": "Manual", "NumberPorts": "2", "BodyType": "Hatchback", "VehicleAttributes": [{"Name": "Aceita troca"}], "Armored": "N", "Color": {"IdPrimary": "30409", "Primary": "Prata"}}, "Seller": {"Id": 3849782, "SellerType": "PJ", "City": "S\u00e3o Paulo", "State": "S\u00e3o Paulo (SP)", "AdType": {"id": 1, "Value": "Loja"}, "BudgetInvestimento": 1, "DealerScore": 0, "CarDelivery": false, "TrocaComTroco": false, "ExceededPlan": false, "FantasyName": "ARENA MOTORS", "Localization": [{"State": "S\u00e3o Paulo (SP)", "City": "S\u00e3o Paulo", "Country": "Brasil", "Neighborhood": "Santo Amaro", "ZipCode": "04708010", "AbbrState": "Av Na\u00e7\u00f5es Unidas 22540"}]}, "Prices": {"Price": 41990.0, "SearchPrice": 41990.0}, "ListingType": "U", "ProductCode": "1785", "Channels": [{"id": 48, "Value": "Webmotors"}], "FipePercent": 105, "IsElegibleVehicleInspection": false, "IsElegible360View": false}}, "51504606": {"ad_url": "https://www.webmotors.com.br/comprar/fiat/500/14-cult-8v-flex-2p-manual/2-portas/2011-2012/51504606", "car": {"UniqueId": 51504606, "PhotoPath": "2024\\202404\\20240404\\fiat-500-1.4-cult-8v-flex-2p-manual-WMIMAGEM23501798573.jpg", "Specification": {"Title": "FIAT 500 1.4 CULT 8V FLEX 2P MANUAL", "Make": {"id": 4, "Value": "FIAT"}, "Model": {"id": 2978, "Value": "500"}, "Version": {"id": 343961, "Value": "1.4 CULT 8V FLEX 2P MANUAL"}, "YearFabrication": "2011", "YearModel": 2012.0, "Odometer": 93000.0, "Transmission": "Manual", "NumberPorts": "2", "BodyType": "Hatchback", "VehicleAttributes": [{"Name": "\u00danico dono"}, {"Name": "IPVA pago"}, {"Name": "Licenciado"}], "Armored": "N", "Color": {"IdPrimary": "30404", "Primary": "Branco"}}, "Seller": {"Id": 8094420, "SellerType": "PF", "City": "S\u00e3o Paulo", "State": "S\u00e3o Paulo (SP)", "AdType": {"id": 4, "Value": "Pessoa F\u00edsica"}, "BudgetInvestimento": 0, "DealerScore": 0, "CarDelivery": false, "TrocaComTroco": false, "ExceededPlan": false, "Localization": [{"State": "S\u00e3o Paulo (SP)", "City": "S\u00e3o Paulo", "Country": "Brasil", "Neighborhood": "", "ZipCode": "04289137", "AbbrState": "SP"}]}, "Prices": {"Price": 42000.0, "SearchPrice": 42000.0}, "ListingType": "U", "ProductCode": "1245", "Channels": [{"id": 48, "Value": "Webmotors"}], "LongComment": "\u00danico dono, todo revisado, tudo documentado, em excelente estado de conserva\u00e7\u00e3o.  N\u00c3O ACEITO CONSIGNA\u00c7\u00c3O, INTERMEDIA\u00c7\u00c3O, NEM TROCAS.  WhatsApp 011971878884 Milton ", "FipePercent": 105, "IsElegibleVehicleInspection": false, "IsElegible360View": false}}, "48682492": {"ad_url": "https://www.webmotors.com.br/comprar/fiat/500/14-cult-8v-flex-2p-manual/2-portas/2011-2012/48682492", "car": {"UniqueId": 48682492, "PhotoPath": "2024\\202402\\20240207\\fiat-500-1.4-cult-8v-flex-2p-manual-wmimagem16385995816.jpg", "Specification": {"Title": "FIAT 500 1.4 CULT 8V FLEX 2P MANUAL", "Make": {"id": 4, "Value": "FIAT"}, "Model": {"id": 2978, "Value": "500"}, "Version": {"id": 343961, "Value": "1.4 CULT 8V FLEX 2P MANUAL"}, "YearFabrication": "2011", "YearModel": 2012.0, "Odometer": 90000.0, "Transmission": "Manual", "NumberPorts": "2", "BodyType": "Hatchback", "VehicleAttributes": [{"Name": "Aceita troca"}], "Armored": "N", "Color": {"IdPrimary": "30405", "Primary": "Cinza"}}, "Seller": {"Id": 3911189, "SellerType": "PJ", "City": "Bariri", "State": "S\u00e3o Paulo (SP)", "AdType": {"id": 1, "Value": "Loja"}, "BudgetInvestimento": 0, "DealerScore": 0, "CarDelivery": false, "TrocaComTroco": false, "ExceededPlan": false, "FantasyName": "RAFFICK AUTOS", "Localization": [{"State": "S\u00e3o Paulo (SP)", "City": "Bariri", "Country": "Brasil", "Neighborhood": "CENTRO", "ZipCode": "17250000", "AbbrState": "RUA XV DE NOVEMBRO , 1643"}]}, "Prices": {"Price": 39900.0, "SearchPrice": 39900.0}, "ListingType": "U", "ProductCode": "1614", "Channels": [{"id": 48, "Value": "Webmotors"}], "LongComment": "\u201cVeiculo Vistoriado e Periciado em excelente estado de conserva\u00e7\u00e3o. Pegamos seu usado como parte de pagamento e financiamos com as melhores taxas do mercado. Raffickautos. Tradi\u00e7\u00e3o e Seguran\u00e7a.\u201d Mais opcionais: Completo. Publica\u00e7\u00e3o autom\u00e1tica atrav\u00e9s do sistema Altimus.", "FipePercent": 99, "GoodDeal": true, "IsElegibleVehicleInspection": false, "IsElegible360View": false}}, "46784845": {"ad_url": "https://www.webmotors.com.br/comprar/fiat/500/14-cult-8v-flex-2p-manual/2-portas/2011-2011/46784845", "car": {"UniqueId": 46784845, "PhotoPath": "2023\\202305\\20230507\\fiat-500-1.4-cult-8v-flex-2p-manual-WMIMAGEM12141539022.jpg", "Specification": {"Title": "FIAT 500 1.4 CULT 8V FLEX 2P MANUAL", "Make": {"id": 4, "Value": "FIAT"}, "Model": {"id": 2978, "Value": "500"}, "Version": {"id": 343961, "Value": "1.4 CULT 8V FLEX 2P MANUAL"}, "YearFabrication": "2011", "YearModel": 2011.0, "Odometer": 85000.0, "Transmission": "Manual", "NumberPorts": "2", "BodyType": "Hatchback", "VehicleAttributes": [{"Name": "Aceita troca"}, {"Name": "IPVA pago"}, {"Name": "Alienado"}, {"Name": "Licenciado"}], "Armored": "N", "Color": {"IdPrimary": "30410", "Primary": "Preto"}}, "Seller": {"Id": 23387224, "SellerType": "PF", "City": "S\u00e3o Paulo", "State": "S\u00e3o Paulo (SP)", "AdType": {"id": 4, "Value": "Pessoa F\u00edsica"}, "BudgetInvestimento": 0, "DealerScore": 0, "CarDelivery": false, "TrocaComTroco": false, "ExceededPlan": false, "Localization": [{"State": "S\u00e3o Paulo (SP)", "City": "S\u00e3o Paulo", "Country": "Brasil", "Neighborhood": "", "ZipCode": "05432011", "AbbrState": "SP"}]}, "Prices": {"Price": 38900.0, "SearchPrice": 38900.0}, "ListingType": "U", "ProductCode": "1245", "Channels": [{"id": 48, "Value": "Webmotors"}], "LongComment": "\u00c9 um excelente carro para quem est\u00e1 buscando um modelo atual, econ\u00f4mico e ideal para cidade.  Est\u00e1 totalmente revisado e novo.  ", "IsElegibleVehicleInspection": false, "IsElegible360View": false}}, "52310605": {"ad_url": "https://www.webmotors.com.br/comprar/fiat/500/14-cult-8v-flex-2p-manual/2-portas/2012-2012/52310605", "car": {"UniqueId": 52310605, "PhotoPath": "2024\\202405\\20240522\\fiat-500-1.4-cult-8v-flex-2p-manual-WMIMAGEM04595681732.jpg", "Specification": {"Title": "FIAT 500 1.4 CULT 8V FLEX 2P MANUAL", "Make": {"id": 4, "Value": "FIAT"}, "Model": {"id": 2978, "Value": "500"}, "Version": {"id": 343961, "Value": "1.4 CULT 8V FLEX 2P MANUAL"}, "YearFabrication": "2012", "YearModel": 2012.0, "Odometer": 81558.0, "Transmission": "Manual", "NumberPorts": "2", "BodyType": "Hatchback", "VehicleAttributes": [{"Name": "IPVA pago"}, {"Name": "Licenciado"}], "Armored": "N", "Color": {"IdPrimary": "30413", "Primary": "Vermelho"}}, "Seller": {"Id": 10359259, "SellerType": "PF", "City": "S\u00e3o Bernardo do Campo", "State": "S\u00e3o Paulo (SP)", "AdType": {"id": 4, "Value": "Pessoa F\u00edsica"}, "BudgetInvestimento": 0, "DealerScore": 0, "CarDelivery": false, "TrocaComTroco": false, "ExceededPlan": false, "Localization": [{"State": "S\u00e3o Paulo (SP)", "City": "S\u00e3o Bernardo do Campo", "Country": "Brasil", "Neighborhood": "", "ZipCode": "09624060", "AbbrState": "SP"}]}, "Prices": {"Price": 39500.0, "SearchPrice": 39500.0}, "ListingType": "U", "ProductCode": "1236", "Channels": [{"id": 48, "Value": "Webmotors"}], "LongComment": "Fiat 500 Cult 1.  4 \u2013 Baixo KM / Manuten\u00e7\u00f5es em dia / Dire\u00e7\u00e3o el\u00e9trica / Ar condicionado / Air bag duplo / Vidros e Travas el\u00e9tricas / Farol de milha / Freio a disco nas quatro rodas /\tAssistente de subida / Computador de bordo / Pneus Dianteiros Novos / Todo original /\tPlaca Mercosul /\tBaixo KM /\tManuten\u00e7\u00f5es em dia (N\u00c3O ACEITO TROCAS, APENAS VENDA) ", "FipePercent": 98, "GoodDeal": true, "IsElegibleVehicleInspection": false, "IsElegible360View": false}}, "51869833": {"ad_url": "https://www.webmotors.com.br/comprar/fiat/500/14-sport-air-16v-gasolina-2p-manual/2-portas/2011-2012/51869833", "car": {"UniqueId": 51869833, "PhotoPath": "2024/202404/20240426/fiat-500-1-4-sport-air-16v-gasolina-2p-manual-wmimagem14575510036.webp", "Specification": {"Title": "FIAT 500 1.4 SPORT AIR 16V GASOLINA 2P MANUAL", "Make": {"id": 4, "Value": "FIAT"}, "Model": {"id": 2978, "Value": "500"}, "Version": {"id": 343964, "Value": "1.4 SPORT AIR 16V GASOLINA 2P MANUAL"}, "YearFabrication": "2011", "YearModel": 2012.0, "Odometer": 78642.0, "Transmission": "Manual", "NumberPorts": "2", "BodyType": "Hatchback", "VehicleAttributes": [{"Name": "Aceita troca"}, {"Name": "IPVA pago"}, {"Name": "Licenciado"}], "Armored": "N", "Color": {"IdPrimary": "30413", "Primary": "Vermelho"}}, "Seller": {"Id": 3879061, "SellerType": "PJ", "City": "S\u00e3o Paulo", "State": "S\u00e3o Paulo (SP)", "AdType": {"id": 1, "Value": "Loja"}, "BudgetInvestimento": 1, "DealerScore": 0, "CarDelivery": true, "TrocaComTroco": true, "ExceededPlan": false, "FantasyName": "Israel Multimarcas", "Localization": [{"State": "S\u00e3o Paulo (SP)", "City": "S\u00e3o Paulo", "Country": "Brasil", "Neighborhood": "Prq Maria Luiza", "ZipCode": "03450000", "AbbrState": "Av.Itaquera, 352"}]}, "Prices": {"Price": 42000.0, "SearchPrice": 42000.0}, "ListingType": "U", "ProductCode": "1785", "Channels": [{"id": 48, "Value": "Webmotors"}], "LongComment": "Veiculo tem passagem de leil\u00e3o sinistro, por\u00e9m esta todo revisado, documenta\u00e7\u00e3o ok, aceito troca e financiamento banc\u00e1rio.  Outros Opcionais: Farol de neblina, Dire\u00e7\u00e3o El\u00e9trica, Banco bi-partido, Controle de estabilidade, Distribui\u00e7\u00e3o eletr\u00f4nica de frenagem, MP3 Player, P\u00e1ra-choques na cor do ve\u00edculo.", "FipePercent": 97, "GoodDeal": true, "IsElegibleVehicleInspection": false, "IsElegible360View": false}}, "50544171": {"ad_url": "https://www.webmotors.com.br/comprar/fiat/500/14-cult-8v-flex-2p-manual/2-portas/2012-2012/50544171", "car": {"UniqueId": 50544171, "PhotoPath": "2024\\202402\\20240214\\fiat-500-1.4-cult-8v-flex-2p-manual-WMIMAGEM13515906958.jpg", "Specification": {"Title": "FIAT 500 1.4 CULT 8V FLEX 2P MANUAL", "Make": {"id": 4, "Value": "FIAT"}, "Model": {"id": 2978, "Value": "500"}, "Version": {"id": 343961, "Value": "1.4 CULT 8V FLEX 2P MANUAL"}, "YearFabrication": "2012", "YearModel": 2012.0, "Odometer": 91000.0, "Transmission": "Manual", "NumberPorts": "2", "BodyType": "Hatchback", "VehicleAttributes": [{"Name": "Aceita troca"}, {"Name": "IPVA pago"}], "Armored": "N", "Color": {"IdPrimary": "30409", "Primary": "Prata"}}, "Seller": {"Id": 7858418, "SellerType": "PF", "City": "S\u00e3o Paulo", "State": "S\u00e3o Paulo (SP)", "AdType": {"id": 4, "Value": "Pessoa F\u00edsica"}, "BudgetInvestimento": 0, "DealerScore": 0, "CarDelivery": false, "TrocaComTroco": false, "ExceededPlan": false, "Localization": [{"State": "S\u00e3o Paulo (SP)", "City": "S\u00e3o Paulo", "Country": "Brasil", "Neighborhood": "", "ZipCode": "04131040", "AbbrState": "SP"}]}, "Prices": {"Price": 39900.0, "SearchPrice": 39900.0}, "ListingType": "U", "ProductCode": "1245", "Channels": [{"id": 48, "Value": "Webmotors"}], "LongComment": "Carro de n\u00e3o-fumante, super confort\u00e1vel e bem cuidado.  Excelente mec\u00e2nica.  N\u00e3o aceito troca / consigna\u00e7\u00e3o.  ", "FipePercent": 99, "GoodDeal": true, "IsElegibleVehicleInspection": false, "IsElegible360View": false}}, "52496153": {"ad_url": "https://www.webmotors.com.br/comprar/fiat/500/14-cult-8v-flex-2p-manual/2-portas/2012-2012/52496153", "car": {"UniqueId": 52496153, "PhotoPath": "2024\\202406\\20240601\\fiat-500-1.4-cult-8v-flex-2p-manual-WMIMAGEM07553667450.jpg", "Specification": {"Title": "FIAT 500 1.4 CULT 8V FLEX 2P MANUAL", "Make": {"id": 4, "Value": "FIAT"}, "Model": {"id": 2978, "Value": "500"}, "Version": {"id": 343961, "Value": "1.4 CULT 8V FLEX 2P MANUAL"}, "YearFabrication": "2012", "YearModel": 2012.0, "Odometer": 71000.0, "Transmission": "Manual", "NumberPorts": "2", "BodyType": "Hatchback", "VehicleAttributes": [{"Name": "IPVA pago"}, {"Name": "Licenciado"}], "Armored": "N", "Color": {"IdPrimary": "30404", "Primary": "Branco"}}, "Seller": {"Id": 26730932, "SellerType": "PF", "City": "S\u00e3o Paulo", "State": "S\u00e3o Paulo (SP)", "AdType": {"id": 4, "Value": "Pessoa F\u00edsica"}, "BudgetInvestimento": 0, "DealerScore": 0, "CarDelivery": false, "TrocaComTroco": false, "ExceededPlan": false, "Localization": [{"State": "S\u00e3o Paulo (SP)", "City": "S\u00e3o Paulo", "Country": "Brasil", "Neighborhood": "", "ZipCode": "05583000", "AbbrState": "SP"}]}, "Prices": {"Price": 38500.0, "SearchPrice": 38500.0}, "ListingType": "U", "ProductCode": "1236", "Channels": [{"id": 48, "Value": "Webmotors"}], "FipePercent": 96, "GoodDeal": true, "IsElegibleVehicleInspection": false, "IsElegible360View": false}}, "52150807": {"ad_url": "https://www.webmotors.com.br/comprar/fiat/500/14-cult-8v-flex-2p-manual/2-portas/2012-2012/52150807", "car": {"UniqueId": 52150807, "PhotoPath": "2024\\202405\\20240513\\fiat-500-1.4-cult-8v-flex-2p-manual-wmimagem1546012329.jpg", "Specification": {"Title": "FIAT 500 1.4 CULT 8V FLEX 2P MANUAL", "Make": {"id": 4, "Value": "FIAT"}, "Model": {"id": 2978, "Value": "500"}, "Version": {"id": 343961, "Value": "1.4 CULT 8V FLEX 2P MANUAL"}, "YearFabrication": "2012", "YearModel": 2012.0, "Odometer": 92000.0, "Transmission": "Manual", "NumberPorts": "2", "BodyType": "Hatchback", "VehicleAttributes": [{"Name": "Aceita troca"}], "Armored": "N", "Color": {"IdPrimary": "30413", "Primary": "Vermelho"}}, "Seller": {"Id": 3919408, "SellerType": "PJ", "City": "Osasco", "State": "S\u00e3o Paulo (SP)", "AdType": {"id": 1, "Value": "Loja"}, "BudgetInvestimento": 1, "DealerScore": 0, "CarDelivery": false, "TrocaComTroco": false, "ExceededPlan": false, "FantasyName": "LIMITED CARS COMERCIO DE VEICULOS LTDA", "Localization": [{"State": "S\u00e3o Paulo (SP)", "City": "Osasco", "Country": "Brasil", "Neighborhood": "Vl Yara", "ZipCode": "06020010", "AbbrState": "Av.dos Autonomistas,  896"}]}, "Prices": {"Price": 42900.0, "SearchPrice": 42900.0}, "ListingType": "U", "ProductCode": "1785", "Channels": [{"id": 48, "Value": "Webmotors"}], "FipePercent": 108, "IsElegibleVehicleInspection": false, "IsElegible360View": false}}, "52464693": {"ad_url": "https://www.webmotors.com.br/comprar/fiat/500/14-cult-8v-flex-2p-manual/2-portas/2012-2012/52464693", "car": {"UniqueId": 52464693, "PhotoPath": "2024/202405/20240529/fiat-500-1-4-cult-8v-flex-2p-manual-wmimagem22474638718.webp", "Specification": {"Title": "FIAT 500 1.4 CULT 8V FLEX 2P MANUAL", "Make": {"id": 4, "Value": "FIAT"}, "Model": {"id": 2978, "Value": "500"}, "Version": {"id": 343961, "Value": "1.4 CULT 8V FLEX 2P MANUAL"}, "YearFabrication": "2012", "YearModel": 2012.0, "Odometer": 92000.0, "Transmission": "Manual", "NumberPorts": "2", "BodyType": "Hatchback", "VehicleAttributes": [{"Name": "Aceita troca"}, {"Name": "IPVA pago"}, {"Name": "Licenciado"}], "Armored": "N", "Color": {"IdPrimary": "30409", "Primary": "Prata"}}, "Seller": {"Id": 3830056, "SellerType": "PJ", "City": "S\u00e3o Paulo", "State": "S\u00e3o Paulo (SP)", "AdType": {"id": 1, "Value": "Loja"}, "BudgetInvestimento": 0, "DealerScore": 0, "CarDelivery": true, "TrocaComTroco": true, "ExceededPlan": false, "FantasyName": "AUTO PARIS", "Localization": [{"State": "S\u00e3o Paulo (SP)", "City": "S\u00e3o Paulo", "Country": "Brasil", "Neighborhood": "IPIRANGA", "ZipCode": "04262200", "AbbrState": "AVENIDA NAZAR\u00c9, 1997"}]}, "Prices": {"Price": 39500.0, "SearchPrice": 39500.0}, "ListingType": "U", "ProductCode": "1614", "Channels": [{"id": 48, "Value": "Webmotors"}], "LongComment": " Outros Opcionais: Farol de neblina, Dire\u00e7\u00e3o El\u00e9trica, Banco bi-partido, Controle de estabilidade, Distribui\u00e7\u00e3o eletr\u00f4nica de frenagem, MP3 Player, P\u00e1ra-choques na cor do ve\u00edculo.", "FipePercent": 98, "GoodDeal": true, "IsElegibleVehicleInspection": false, "IsElegible360View": false}}, "51202731": {"ad_url": "https://www.webmotors.com.br/comprar/fiat/500/14-cult-8v-flex-2p-manual/2-portas/2013-2013/51202731", "car": {"UniqueId": 51202731, "PhotoPath": "2024/202405/20240520/fiat-500-1-4-cult-8v-flex-2p-manual-wmimagem15424150328.webp", "Specification": {"Title": "FIAT 500 1.4 CULT 8V FLEX 2P MANUAL", "Make": {"id": 4, "Value": "FIAT"}, "Model": {"id": 2978, "Value": "500"}, "Version": {"id": 343961, "Value": "1.4 CULT 8V FLEX 2P MANUAL"}, "YearFabrication": "2013", "YearModel": 2013.0, "Odometer": 73650.0, "Transmission": "Manual", "NumberPorts": "2", "BodyType": "Hatchback", "VehicleAttributes": [{"Name": "Aceita troca"}, {"Name": "Todas as revis\u00f5es feitas pela agenda do carro"}, {"Name": "IPVA pago"}], "Armored": "N", "Color": {"IdPrimary": "30404", "Primary": "Branco"}}, "Seller": {"Id": 3919292, "SellerType": "PJ", "City": "Praia Grande", "State": "S\u00e3o Paulo (SP)", "AdType": {"id": 1, "Value": "Loja"}, "BudgetInvestimento": 1, "DealerScore": 0, "CarDelivery": false, "TrocaComTroco": false, "ExceededPlan": false, "FantasyName": "INVICTUS MULTIMARCAS", "Localization": [{"State": "S\u00e3o Paulo (SP)", "City": "Praia Grande", "Country": "Brasil", "Neighborhood": "Boqueir\u00e3o", "ZipCode": "11701335", "AbbrState": "Av.Kennedy, 256"}]}, "Prices": {"Price": 39990.0, "SearchPrice": 39990.0}, "ListingType": "U", "ProductCode": "2611", "Channels": [{"id": 48, "Value": "Webmotors"}], "LongComment": "Per\u00edcia cautelar aprovada \n\nFinanciamos em at\u00e9 60 meses sem entrada  Outros Opcionais: Farol de neblina, Dire\u00e7\u00e3o El\u00e9trica, Comando de \u00e1udio no volante, Banco bi-partido, Controle de estabilidade, Distribui\u00e7\u00e3o eletr\u00f4nica de frenagem, MP3 Player, P\u00e1ra-choques na cor do ve\u00edculo.", "FipePercent": 93, "GoodDeal": true, "IsElegibleVehicleInspection": false, "IsElegible360View": false}}, "49178814": {"ad_url": "https://www.webmotors.com.br/comprar/fiat/500/14-cult-8v-flex-2p-manual/2-portas/2011-2012/49178814", "car": {"UniqueId": 49178814, "PhotoPath": "2023\\202311\\20231109\\fiat-500-1.4-cult-8v-flex-2p-manual-WMIMAGEM21340108779.jpg", "Specification": {"Title": "FIAT 500 1.4 CULT 8V FLEX 2P MANUAL", "Make": {"id": 4, "Value": "FIAT"}, "Model": {"id": 2978, "Value": "500"}, "Version": {"id": 343961, "Value": "1.4 CULT 8V FLEX 2P MANUAL"}, "YearFabrication": "2011", "YearModel": 2012.0, "Odometer": 83000.0, "Transmission": "Manual", "NumberPorts": "2", "BodyType": "Hatchback", "VehicleAttributes": [{"Name": "Aceita troca"}, {"Name": "IPVA pago"}], "Armored": "N", "Color": {"IdPrimary": "30404", "Primary": "Branco"}}, "Seller": {"Id": 22524394, "SellerType": "PF", "City": "S\u00e3o Paulo", "State": "S\u00e3o Paulo (SP)", "AdType": {"id": 4, "Value": "Pessoa F\u00edsica"}, "BudgetInvestimento": 0, "DealerScore": 0, "CarDelivery": false, "TrocaComTroco": false, "ExceededPlan": false, "Localization": [{"State": "S\u00e3o Paulo (SP)", "City": "S\u00e3o Paulo", "Country": "Brasil", "Neighborhood": "", "ZipCode": "02126030", "AbbrState": "SP"}]}, "Prices": {"Price": 39800.0, "SearchPrice": 39800.0}, "ListingType": "U", "ProductCode": "674", "Channels": [{"id": 48, "Value": "Webmotors"}], "LongComment": "Negoci\u00e1vel, aceito troca", "FipePercent": 99, "GoodDeal": true, "IsElegibleVehicleInspection": false, "IsElegible360View": false}}, "51787135": {"ad_url": "https://www.webmotors.com.br/comprar/fiat/500/14-cult-8v-flex-2p-manual/2-portas/2011-2012/51787135", "car": {"UniqueId": 51787135, "PhotoPath": "2024\\202404\\20240422\\fiat-500-1.4-cult-8v-flex-2p-manual-WMIMAGEM09184014980.jpg", "Specification": {"Title": "FIAT 500 1.4 CULT 8V FLEX 2P MANUAL", "Make": {"id": 4, "Value": "FIAT"}, "Model": {"id": 2978, "Value": "500"}, "Version": {"id": 343961, "Value": "1.4 CULT 8V FLEX 2P MANUAL"}, "YearFabrication": "2011", "YearModel": 2012.0, "Odometer": 88996.0, "Transmission": "Manual", "NumberPorts": "2", "BodyType": "Hatchback", "VehicleAttributes": [{"Name": "IPVA pago"}], "Armored": "N", "Color": {"IdPrimary": "30407", "Primary": "Laranja"}}, "Seller": {"Id": 26420783, "SellerType": "PF", "City": "Guaruj\u00e1", "State": "S\u00e3o Paulo (SP)", "AdType": {"id": 4, "Value": "Pessoa F\u00edsica"}, "BudgetInvestimento": 0, "DealerScore": 0, "CarDelivery": false, "TrocaComTroco": false, "ExceededPlan": false, "Localization": [{"State": "S\u00e3o Paulo (SP)", "City": "Guaruj\u00e1", "Country": "Brasil", "Neighborhood": "", "ZipCode": "11440100", "AbbrState": "SP"}]}, "Prices": {"Price": 40000.0, "SearchPrice": 40000.0}, "ListingType": "U", "ProductCode": "1245", "Channels": [{"id": 48, "Value": "Webmotors"}], "LongComment": "Segundo dono, carro de mulher! ", "FipePercent": 100, "IsElegibleVehicleInspection": false, "IsElegible360View": false}}, "52421723": {"ad_url": "https://www.webmotors.com.br/comprar/fiat/500/14-cult-8v-flex-2p-manual/2-portas/2011-2012/52421723", "car": {"UniqueId": 52421723, "PhotoPath": "2024\\202405\\20240527\\fiat-500-1.4-cult-8v-flex-2p-manual-WMIMAGEM16083292924.jpg", "Specification": {"Title": "FIAT 500 1.4 CULT 8V FLEX 2P MANUAL", "Make": {"id": 4, "Value": "FIAT"}, "Model": {"id": 2978, "Value": "500"}, "Version": {"id": 343961, "Value": "1.4 CULT 8V FLEX 2P MANUAL"}, "YearFabrication": "2011", "YearModel": 2012.0, "Odometer": 67337.0, "Transmission": "Manual", "NumberPorts": "2", "BodyType": "Hatchback", "VehicleAttributes": [{"Name": "Aceita troca"}, {"Name": "IPVA pago"}, {"Name": "Licenciado"}], "Armored": "N", "Color": {"IdPrimary": "30404", "Primary": "Branco"}}, "Seller": {"Id": 7963581, "SellerType": "PF", "City": "S\u00e3o Paulo", "State": "S\u00e3o Paulo (SP)", "AdType": {"id": 4, "Value": "Pessoa F\u00edsica"}, "BudgetInvestimento": 0, "DealerScore": 0, "CarDelivery": false, "TrocaComTroco": false, "ExceededPlan": false, "Localization": [{"State": "S\u00e3o Paulo (SP)", "City": "S\u00e3o Paulo", "Country": "Brasil", "Neighborhood": "", "ZipCode": "05307080", "AbbrState": "SP"}]}, "Prices": {"Price": 41500.0, "SearchPrice": 41500.0}, "ListingType": "U", "ProductCode": "1245", "Channels": [{"id": 48, "Value": "Webmotors"}], "FipePercent": 103, "IsElegibleVehicleInspection": false, "IsElegible360View": false}}, "52494241": {"ad_url": "https://www.webmotors.com.br/comprar/fiat/500/14-cult-8v-flex-2p-manual/2-portas/2011-2012/52494241", "car": {"UniqueId": 52494241, "PhotoPath": "2024\\202405\\20240531\\fiat-500-1.4-cult-8v-flex-2p-manual-wmimagem18340488044.jpg", "Specification": {"Title": "FIAT 500 1.4 CULT 8V FLEX 2P MANUAL", "Make": {"id": 4, "Value": "FIAT"}, "Model": {"id": 2978, "Value": "500"}, "Version": {"id": 343961, "Value": "1.4 CULT 8V FLEX 2P MANUAL"}, "YearFabrication": "2011", "YearModel": 2012.0, "Odometer": 99000.0, "Transmission": "Manual", "NumberPorts": "2", "BodyType": "Hatchback", "VehicleAttributes": [{"Name": "Aceita troca"}], "Armored": "N", "Color": {"IdPrimary": "30409", "Primary": "Prata"}}, "Seller": {"Id": 3849782, "SellerType": "PJ", "City": "S\u00e3o Paulo", "State": "S\u00e3o Paulo (SP)", "AdType": {"id": 1, "Value": "Loja"}, "BudgetInvestimento": 1, "DealerScore": 0, "CarDelivery": false, "TrocaComTroco": false, "ExceededPlan": false, "FantasyName": "ARENA MOTORS", "Localization": [{"State": "S\u00e3o Paulo (SP)", "City": "S\u00e3o Paulo", "Country": "Brasil", "Neighborhood": "Santo Amaro", "ZipCode": "04708010", "AbbrState": "Av Na\u00e7\u00f5es Unidas 22540"}]}, "Prices": {"Price": 41990.0, "SearchPrice": 41990.0}, "ListingType": "U", "ProductCode": "1785", "Channels": [{"id": 48, "Value": "Webmotors"}], "FipePercent": 105, "IsElegibleVehicleInspection": false, "IsElegible360View": false}}, "48293821": {"ad_url": "https://www.webmotors.com.br/comprar/fiat/500/14-cult-8v-flex-2p-manual/2-portas/2013-2013/48293821", "car": {"UniqueId": 48293821, "PhotoPath": "2024\\202404\\20240421\\fiat-500-1.4-cult-8v-flex-2p-manual-WMIMAGEM22194769528.jpg", "Specification": {"Title": "FIAT 500 1.4 CULT 8V FLEX 2P MANUAL", "Make": {"id": 4, "Value": "FIAT"}, "Model": {"id": 2978, "Value": "500"}, "Version": {"id": 343961, "Value": "1.4 CULT 8V FLEX 2P MANUAL"}, "YearFabrication": "2013", "YearModel": 2013.0, "Odometer": 91000.0, "Transmission": "Manual", "NumberPorts": "2", "BodyType": "Hatchback", "VehicleAttributes": [{"Name": "Aceita troca"}, {"Name": "Todas as revis\u00f5es feitas pela agenda do carro"}, {"Name": "Todas as revis\u00f5es feitas pela concession\u00e1ria"}, {"Name": "IPVA pago"}, {"Name": "Licenciado"}], "Armored": "N", "Color": {"IdPrimary": "30405", "Primary": "Cinza"}}, "Seller": {"Id": 24680279, "SellerType": "PF", "City": "S\u00e3o Paulo", "State": "S\u00e3o Paulo (SP)", "AdType": {"id": 4, "Value": "Pessoa F\u00edsica"}, "BudgetInvestimento": 0, "DealerScore": 0, "CarDelivery": false, "TrocaComTroco": false, "ExceededPlan": false, "Localization": [{"State": "S\u00e3o Paulo (SP)", "City": "S\u00e3o Paulo", "Country": "Brasil", "Neighborhood": "", "ZipCode": "04044010", "AbbrState": "SP"}]}, "Prices": {"Price": 41700.0, "SearchPrice": 41700.0}, "ListingType": "U", "ProductCode": "1236", "Channels": [{"id": 48, "Value": "Webmotors"}], "LongComment": "Carro de Garagem, pneus novos revisado Suspen\u00e7\u00e3o revisada Comando no volante Roda liga leve Bancos internos em perfeito estado Chave reserva e manual Radio Original 500 Obs: n\u00e3o est\u00e1 autorizado divulgar ou replicar o conte\u00fado desta publica\u00e7\u00e3o, a venda \u00e9 feita diretamente com propriet\u00e1rio do ve\u00edculo.  ", "FipePercent": 97, "GoodDeal": true, "IsElegibleVehicleInspection": false, "IsElegible360View": false}}, "51675010": {"ad_url": "https://www.webmotors.com.br/comprar/fiat/500/14-cult-8v-flex-2p-manual/2-portas/2012-2012/51675010", "car": {"UniqueId": 51675010, "PhotoPath": "2024\\202404\\20240415\\fiat-500-1.4-cult-8v-flex-2p-manual-WMIMAGEM15271337035.jpg", "Specification": {"Title": "FIAT 500 1.4 CULT 8V FLEX 2P MANUAL", "Make": {"id": 4, "Value": "FIAT"}, "Model": {"id": 2978, "Value": "500"}, "Version": {"id": 343961, "Value": "1.4 CULT 8V FLEX 2P MANUAL"}, "YearFabrication": "2012", "YearModel": 2012.0, "Odometer": 86793.0, "Transmission": "Manual", "NumberPorts": "2", "BodyType": "Hatchback", "VehicleAttributes": [{"Name": "Aceita troca"}, {"Name": "IPVA pago"}, {"Name": "Licenciado"}], "Armored": "N", "Color": {"IdPrimary": "30413", "Primary": "Vermelho"}}, "Seller": {"Id": 14684508, "SellerType": "PF", "City": "S\u00e3o Paulo", "State": "S\u00e3o Paulo (SP)", "AdType": {"id": 4, "Value": "Pessoa F\u00edsica"}, "BudgetInvestimento": 0, "DealerScore": 0, "CarDelivery": false, "TrocaComTroco": false, "ExceededPlan": false, "Localization": [{"State": "S\u00e3o Paulo (SP)", "City": "S\u00e3o Paulo", "Country": "Brasil", "Neighborhood": "", "ZipCode": "04457120", "AbbrState": "SP"}]}, "Prices": {"Price": 37800.0, "SearchPrice": 37800.0}, "ListingType": "U", "ProductCode": "1245", "Channels": [{"id": 48, "Value": "Webmotors"}], "LongComment": "Ve\u00edculo completo, com ar condic, ABS, vidros e travas el\u00e9tricos, controle de estabilidade etc.  Com chave reserva e manual do propriet\u00e1rio.  ", "FipePercent": 94, "GoodDeal": true, "IsElegibleVehicleInspection": false, "IsElegible360View": false}}, "52439002": {"ad_url": "https://www.webmotors.com.br/comprar/fiat/500/14-cult-8v-flex-2p-manual/2-portas/2013-2013/52439002", "car": {"UniqueId": 52439002, "PhotoPath": "2024\\202405\\20240528\\fiat-500-1.4-cult-8v-flex-2p-manual-wmimagem15262163962.jpg", "Specification": {"Title": "FIAT 500 1.4 CULT 8V FLEX 2P MANUAL", "Make": {"id": 4, "Value": "FIAT"}, "Model": {"id": 2978, "Value": "500"}, "Version": {"id": 343961, "Value": "1.4 CULT 8V FLEX 2P MANUAL"}, "YearFabrication": "2013", "YearModel": 2013.0, "Odometer": 97050.0, "Transmission": "Manual", "NumberPorts": "2", "BodyType": "Hatchback", "VehicleAttributes": [{"Name": "Aceita troca"}, {"Name": "IPVA pago"}, {"Name": "Licenciado"}], "Armored": "N", "Color": {"IdPrimary": "30413", "Primary": "Vermelho"}}, "Seller": {"Id": 3955121, "SellerType": "PJ", "City": "S\u00e3o Paulo", "State": "S\u00e3o Paulo (SP)", "AdType": {"id": 1, "Value": "Loja"}, "BudgetInvestimento": 0, "DealerScore": 0, "CarDelivery": false, "TrocaComTroco": false, "ExceededPlan": false, "FantasyName": "PULSE MULTIMARCAS", "Localization": [{"State": "S\u00e3o Paulo (SP)", "City": "S\u00e3o Paulo", "Country": "Brasil", "Neighborhood": "Vl Prel", "ZipCode": "05777001", "AbbrState": "Est.do Campo Limpo, 2215"}]}, "Prices": {"Price": 41900.0, "SearchPrice": 41900.0}, "ListingType": "U", "ProductCode": "4675", "Channels": [{"id": 48, "Value": "Webmotors"}], "LongComment": "* Simula\u00e7\u00e3o por ******* sem compromisso", "FipePercent": 97, "GoodDeal": true, "IsElegibleVehicleInspection": false, "IsElegible360View": false}}, "52283307": {"ad_url": "https://www.webmotors.com.br/comprar/fiat/500/14-cult-8v-flex-2p-manual/2-portas/2011-2012/52283307", "car": {"UniqueId": 52283307, "PhotoPath": "2024\\202405\\20240520\\fiat-500-1.4-cult-8v-flex-2p-manual-WMIMAGEM16532713434.jpg", "Specification": {"Title": "FIAT 500 1.4 CULT 8V FLEX 2P MANUAL", "Make": {"id": 4, "Value": "FIAT"}, "Model": {"id": 2978, "Value": "500"}, "Version": {"id": 343961, "Value": "1.4 CULT 8V FLEX 2P MANUAL"}, "YearFabrication": "2011", "YearModel": 2012.0, "Odometer": 160.0, "Transmission": "Manual", "NumberPorts": "2", "BodyType": "Hatchback", "VehicleAttributes": [{"Name": "IPVA pago"}, {"Name": "Licenciado"}], "Armored": "N", "Color": {"IdPrimary": "30402", "Primary": "Azul"}}, "Seller": {"Id": 26468181, "SellerType": "PF", "City": "S\u00e3o Paulo", "State": "S\u00e3o Paulo (SP)", "AdType": {"id": 4, "Value": "Pessoa F\u00edsica"}, "BudgetInvestimento": 0, "DealerScore": 0, "CarDelivery": false, "TrocaComTroco": false, "ExceededPlan": false, "Localization": [{"State": "S\u00e3o Paulo (SP)", "City": "S\u00e3o Paulo", "Country": "Brasil", "Neighborhood": "", "ZipCode": "04803000", "AbbrState": "SP"}]}, "Prices": {"Price": 39500.0, "SearchPrice": 39500.0}, "ListingType": "U", "ProductCode": "1245", "Channels": [{"id": 48, "Value": "Webmotors"}], "LongComment": "Carro completo, doc.  em dia, alarme, r\u00e1dio original da Fiat, Manual do carro mais chave reserva.  ", "FipePercent": 98, "GoodDeal": true, "IsElegibleVehicleInspection": false, "IsElegible360View": false}}, "52186629": {"ad_url": "https://www.webmotors.com.br/comprar/fiat/500/14-cult-8v-flex-2p-manual/2-portas/2011-2012/52186629", "car": {"UniqueId": 52186629, "PhotoPath": "2024\\202405\\20240515\\FIAT-500-1.4-CULT-8V-FLEX-2P-MANUAL-wmimagem11025646114.jpg", "Specification": {"Title": "FIAT 500 1.4 CULT 8V FLEX 2P MANUAL", "Make": {"id": 4, "Value": "FIAT"}, "Model": {"id": 2978, "Value": "500"}, "Version": {"id": 343961, "Value": "1.4 CULT 8V FLEX 2P MANUAL"}, "YearFabrication": "2011", "YearModel": 2012.0, "Odometer": 93000.0, "Transmission": "Manual", "NumberPorts": "2", "BodyType": "Hatchback", "VehicleAttributes": [{"Name": "Aceita troca"}], "Armored": "N", "Color": {"IdPrimary": "30404", "Primary": "Branco"}}, "Seller": {"Id": 3877877, "SellerType": "PJ", "City": "S\u00e3o Paulo", "State": "S\u00e3o Paulo (SP)", "AdType": {"id": 1, "Value": "Loja"}, "BudgetInvestimento": -1, "DealerScore": 0, "CarDelivery": true, "TrocaComTroco": true, "ExceededPlan": false, "FantasyName": "IMP\u00c9RIO AUTOM\u00d3VEIS", "Localization": [{"State": "S\u00e3o Paulo (SP)", "City": "S\u00e3o Paulo", "Country": "Brasil", "Neighborhood": "Vl Graciosa", "ZipCode": "03295000", "AbbrState": "Av.Luiz Ign\u00e1cio Anhaia Mello, 4470"}]}, "Prices": {"Price": 39990.0, "SearchPrice": 39990.0}, "ListingType": "U", "ProductCode": "2612", "Channels": [{"id": 48, "Value": "Webmotors"}], "LongComment": "Imp\u00e9rio Autom\u00f3veis:\n\n-Temos proced\u00eancia, qualidade, experi\u00eancia para fazer o melhor neg\u00f3cio com nossos clientes. \n\n-Aceitamos o seu usado mesmo com d\u00edvidas. Melhor avalia\u00e7\u00e3o do mercado!\n\nPROCURAR PELOS VENDEDORES FELIPE OU LUIZ\n\nN\u00c3O POSSU\u00cdMOS NENHUMA FILIAL!\n\nNos reservamos ao direito de corrigir eventuais erros na digita\u00e7\u00e3o. Condi\u00e7\u00f5es sujeitas \u00e0 altera\u00e7\u00e3o sem pr\u00e9vio aviso.\n", "FipePercent": 100, "IsElegibleVehicleInspection": false, "IsElegible360View": false}}, "41458066": {"ad_url": "https://www.webmotors.com.br/comprar/fiat/500/14-cult-8v-flex-2p-manual/0-portas/2012-2012/41458066", "car": {"UniqueId": 41458066, "PhotoPath": "2022\\202209\\20220909\\fiat-500-1.4-cult-8v-flex-2p-manual-WMIMAGEM22525153515.jpg", "Specification": {"Title": "FIAT 500 1.4 CULT 8V FLEX 2P MANUAL", "Make": {"id": 4, "Value": "FIAT"}, "Model": {"id": 2978, "Value": "500"}, "Version": {"id": 343961, "Value": "1.4 CULT 8V FLEX 2P MANUAL"}, "YearFabrication": "2012", "YearModel": 2012.0, "Odometer": 77900.0, "Transmission": "Manual", "NumberPorts": "0", "BodyType": "Hatchback", "VehicleAttributes": [{"Name": "Aceita troca"}], "Armored": "N", "Color": {"IdPrimary": "30410", "Primary": "Preto"}}, "Seller": {"Id": 15192661, "SellerType": "PF", "City": "Guarulhos", "State": "S\u00e3o Paulo (SP)", "AdType": {"id": 4, "Value": "Pessoa F\u00edsica"}, "BudgetInvestimento": 0, "DealerScore": 0, "CarDelivery": false, "TrocaComTroco": false, "ExceededPlan": false, "Localization": [{"State": "S\u00e3o Paulo (SP)", "City": "Guarulhos", "Country": "Brasil", "Neighborhood": "", "ZipCode": "07114180", "AbbrState": "SP"}]}, "Prices": {"Price": 42500.0, "SearchPrice": 42500.0}, "ListingType": "U", "ProductCode": "1245", "Channels": [{"id": 48, "Value": "Webmotors"}], "LongComment": "Dos \u00faltimos FIAT 500 na cor PRETA com TETO SOLAR, SOM DA BOSE E BANCO DE COURO e BAIXO KM que tem hoje a venda.  APROVEITA QUE AINDA ESTA A VENDA, AT\u00c9 PR\u00d3XIMOS DIAS, se n\u00e3o vender vou deix\u00e1-lo destin\u00e1-lo a deixar em local de carros retr\u00f4 apenas para apresenta\u00e7\u00e3o e n\u00e3o venda.  O valor \u00e9 apenas o anunciado.  Use a webmotors e coloque o filtro: Fiat 500 + ano 2012 + teto solar + banco de couro.  Op\u00e7\u00f5es mais caras do que ele.  Se tem real interesse para compra, pode contatar direto (11) 988203304.  ", "FipePercent": 106, "IsElegibleVehicleInspection": false, "IsElegible360View": false}}, "info": {"lastUpdateDateTime": "02_06_2024-12_02", "foundResultsIds": ["49101241", "52457664", "49880208", "52461247", "51504606", "48682492", "46784845", "52310605", "51869833", "50544171", "52496153", "52150807", "52464693", "51202731", "49178814", "51787135", "52421723", "52494241", "48293821", "51675010", "52439002", "52283307", "52186629", "41458066"], "foundResultsSize": 24}}